buildsys_dateversion/__init__.py
buildsys_dateversion/_hooks.py
buildsys_dateversion-2025.10.dist-info/licenses/LICENSE
buildsys_dateversion-2025.10.dist-info/METADATA
buildsys_dateversion-2025.10.dist-info/WHEEL
buildsys_dateversion-2025.10.dist-info/top_level.txt
buildsys_dateversion-2025.10.dist-info/RECORD
