Metadata-Version: 2.4
Name: buildsys-dateversion
Version: 2025.10
Summary: Easy date-based versioning for Python projects
Author-email: Rohan McGovern <rohan@mcgovern.id.au>
Maintainer-email: Rohan McGovern <rohan@mcgovern.id.au>
License:                     GNU GENERAL PUBLIC LICENSE
Project-URL: homepage, https://github.com/rohanpm/buildsys-dateversion
Requires-Python: >=3.8
License-File: LICENSE
Requires-Dist: tomli>=2.0.1; python_version < "3.11"
Dynamic: license-file
